arpitcalc/__init__.py
arpitcalc-0.1.dist-info/LICENCE.txt
arpitcalc-0.1.dist-info/METADATA
arpitcalc-0.1.dist-info/WHEEL
arpitcalc-0.1.dist-info/top_level.txt
arpitcalc-0.1.dist-info/RECORD
