Metadata-Version: 2.1
Name: arpitcalc
Version: 0.1
Summary: basic calculator
Home-page: UNKNOWN
Author: Arpit Jain
Author-email: arpit456jain@gmail.com
License: UNKNOWN
Platform: UNKNOWN
Classifier: Programming Language :: Python :: 3
Classifier: License :: OSI Approved :: MIT License
Classifier: Operating System :: OS Independent
